LICENSE
MANIFEST.in
README.md
setup.cfg
setup.py
examples/example1.py
examples/sample-nonspam.txt
examples/sample-spam.txt
spamc/__init__.py
spamc/backend_eventlet.py
spamc/backend_gevent.py
spamc/backend_thread.py
spamc/client.py
spamc/conn.py
spamc/exceptions.py
spamc/regex.py
spamc/utils.py
spamc/version.py
spamc.egg-info/PKG-INFO
spamc.egg-info/SOURCES.txt
spamc.egg-info/dependency_links.txt
spamc.egg-info/not-zip-safe
spamc.egg-info/top_level.txt