Metadata-Version: 1.1
Name: spamc
Version: 0.0.7
Summary: Python spamassassin spamc client library
Home-page: https://github.com/akissa/spamc
Author: Andrew Colin Kissa
Author-email: andrew@topdog.za.net
License: AGPLv3+
Keywords: spam spamc spamassassin
Platform: UNKNOWN
Classifier: Development Status :: 4 - Beta
Classifier: Programming Language :: Python
Classifier: Programming Language :: Python :: 2.6
Classifier: Programming Language :: Python :: 2.7
Classifier: Topic :: Software Development :: Libraries :: Python Modules
Classifier: Intended Audience :: Developers
Classifier: License :: OSI Approved :: GNU Affero General Public License v3 or later (AGPLv3+)
Classifier: Natural Language :: English
Classifier: Operating System :: OS Independent
